{
  "project_info": {
    "project_number": "1062614738173",
    "project_id": "traces-1a3f2",
    "storage_bucket": "traces-1a3f2.firebasestorage.app"
  },
  "client": [
    {
      "client_info": {
        "mobilesdk_app_id": "1:1062614738173:android:b1b1bc038e8d63c7164a94",
        "android_client_info": {
          "package_name": "com.example.traces"
        }
      },
      "oauth_client": [
        {
          "client_id": "1062614738173-k8iopneh0nofu1bt5g5fn7lftmqg2rm7.apps.googleusercontent.com",
          "client_type": 3
        }
      ],
      "api_key": [
        {
          "current_key": "AIzaSyA7Xr8_kVf3MQJYfHT9C3Y2Z-W-ZVFbvZg"
        }
      ],
      "services": {
        "appinvite_service": {
          "other_platform_oauth_client": [
            {
              "client_id": "1062614738173-k8iopneh0nofu1bt5g5fn7lftmqg2rm7.apps.googleusercontent.com",
              "client_type": 3
            },
            {
              "client_id": "1062614738173-aiq40mrold1c9qrqqr0ls5oqp3s8le94.apps.googleusercontent.com",
              "client_type": 2,
              "ios_info": {
                "bundle_id": "com.example.traces"
              }
            }
          ]
        }
      }
    }
  ],
  "configuration_version": "1"
}